{
  "groups": {
    "120363422626206307@g.us": {
      "antilink": false,
      "welcome": ""
    }
  },
  "users": {
    "6283854136611@s.whatsapp.net": {
      "limit": 20,
      "premium": false
    },
    "184524730298481@lid": {
      "limit": 20,
      "premium": false
    },
    "160636843614348@lid": {
      "limit": 20,
      "premium": false
    },
    "269178602836175@lid": {
      "limit": 20,
      "premium": false
    },
    "100390750134481@lid": {
      "limit": 20,
      "premium": false
    }
  },
  "settings": {}
}